Achilterm-0.21.dist-info/metadata.json
Achilterm-0.21.dist-info/entry_points.txt
Achilterm-0.21.dist-info/top_level.txt
Achilterm-0.21.dist-info/METADATA
Achilterm-0.21.dist-info/DESCRIPTION.rst
Achilterm-0.21.dist-info/RECORD
Achilterm-0.21.dist-info/WHEEL
achilterm/achilterm.css
achilterm/achilterm.html
achilterm/achiltermlite.js
achilterm/achiltermlite.css
achilterm/achiltermlite.html
achilterm/achilterm.py
achilterm/__init__.py
achilterm/achilterm.js
achilterm/achiltorn.py
Achilterm-0.21.data/data/share/man/man1/achilterm.1
